[
  {
    "iteration": 1,
    "subproblem_original_cost": 442.0,
    "num_routes_generated": 5,
    "max_abs_g_i": 1.0,
    "avg_abs_g_i": 0.9211323729436766,
    "max_cap_violation": 0.0,
    "avg_cap_violation": 0.0,
    "is_feasible_overall": false,
    "best_feasible_cost": Infinity,
    "avg_lambda_visit": -0.8484848484848485,
    "avg_rho_visit": 1.0848484848484854,
    "avg_mu_capacity": 0.0,
    "avg_sigma_capacity": 1.0
  },
  {
    "iteration": 2,
    "subproblem_original_cost": 442.0,
    "num_routes_generated": 5,
    "max_abs_g_i": 1.0,
    "avg_abs_g_i": 0.9211323729436766,
    "max_cap_violation": 0.0,
    "avg_cap_violation": 0.0,
    "is_feasible_overall": false,
    "best_feasible_cost": Infinity,
    "avg_lambda_visit": -1.7787878787878795,
    "avg_rho_visit": 1.1778787878787884,
    "avg_mu_capacity": 0.0,
    "avg_sigma_capacity": 1.0
  },
  {
    "iteration": 3,
    "subproblem_original_cost": 444.0,
    "num_routes_generated": 5,
    "max_abs_g_i": 1.0,
    "avg_abs_g_i": 0.9045340337332909,
    "max_cap_violation": 0.0,
    "avg_cap_violation": 0.0,
    "is_feasible_overall": false,
    "best_feasible_cost": Infinity,
    "avg_lambda_visit": -2.765454545454547,
    "avg_rho_visit": 1.276545454545455,
    "avg_mu_capacity": 0.0,
    "avg_sigma_capacity": 1.0
  },
  {
    "iteration": 4,
    "subproblem_original_cost": 442.0,
    "num_routes_generated": 5,
    "max_abs_g_i": 1.0,
    "avg_abs_g_i": 0.9211323729436766,
    "max_cap_violation": 0.0,
    "avg_cap_violation": 0.0,
    "is_feasible_overall": false,
    "best_feasible_cost": Infinity,
    "avg_lambda_visit": -3.8841212121212143,
    "avg_rho_visit": 1.3884121212121225,
    "avg_mu_capacity": 0.0,
    "avg_sigma_capacity": 1.0
  },
  {
    "iteration": 5,
    "subproblem_original_cost": 455.0,
    "num_routes_generated": 5,
    "max_abs_g_i": 1.0,
    "avg_abs_g_i": 0.8528028654224418,
    "max_cap_violation": 0.0,
    "avg_cap_violation": 0.0,
    "is_feasible_overall": false,
    "best_feasible_cost": Infinity,
    "avg_lambda_visit": -4.948921212121213,
    "avg_rho_visit": 1.4948921212121213,
    "avg_mu_capacity": 0.0,
    "avg_sigma_capacity": 1.0
  },
  {
    "iteration": 6,
    "subproblem_original_cost": 562.0,
    "num_routes_generated": 5,
    "max_abs_g_i": 1.0,
    "avg_abs_g_i": 0.30151134457776363,
    "max_cap_violation": 254,
    "avg_cap_violation": 113.59225325698932,
    "is_feasible_overall": false,
    "best_feasible_cost": Infinity,
    "avg_lambda_visit": -5.07683090909091,
    "avg_rho_visit": 1.5076830909090913,
    "avg_mu_capacity": 50.8,
    "avg_sigma_capacity": 1.02
  },
  {
    "iteration": 7,
    "subproblem_original_cost": 569.0,
    "num_routes_generated": 5,
    "max_abs_g_i": 1.0,
    "avg_abs_g_i": 0.24618298195866548,
    "max_cap_violation": 256,
    "avg_cap_violation": 114.48668044798923,
    "is_feasible_overall": false,
    "best_feasible_cost": Infinity,
    "avg_lambda_visit": -5.16384790909091,
    "avg_rho_visit": 1.5163847909090913,
    "avg_mu_capacity": 102.0,
    "avg_sigma_capacity": 1.04
  },
  {
    "iteration": 8,
    "subproblem_original_cost": 554.0,
    "num_routes_generated": 5,
    "max_abs_g_i": 1.0,
    "avg_abs_g_i": 0.4264014327112209,
    "max_cap_violation": 256,
    "avg_cap_violation": 114.48668044798923,
    "is_feasible_overall": false,
    "best_feasible_cost": Infinity,
    "avg_lambda_visit": -5.425299942424243,
    "avg_rho_visit": 1.5425299942424247,
    "avg_mu_capacity": 153.2,
    "avg_sigma_capacity": 1.06
  },
  {
    "iteration": 9,
    "subproblem_original_cost": 569.0,
    "num_routes_generated": 5,
    "max_abs_g_i": 1.0,
    "avg_abs_g_i": 0.24618298195866548,
    "max_cap_violation": 256,
    "avg_cap_violation": 114.48668044798923,
    "is_feasible_overall": false,
    "best_feasible_cost": Infinity,
    "avg_lambda_visit": -5.526923845757577,
    "avg_rho_visit": 1.5526923845757579,
    "avg_mu_capacity": 204.4,
    "avg_sigma_capacity": 1.08
  },
  {
    "iteration": 10,
    "subproblem_original_cost": 572.0,
    "num_routes_generated": 5,
    "max_abs_g_i": 1.0,
    "avg_abs_g_i": 0.17407765595569785,
    "max_cap_violation": 256,
    "avg_cap_violation": 114.48668044798923,
    "is_feasible_overall": false,
    "best_feasible_cost": Infinity,
    "avg_lambda_visit": -5.5983768060909105,
    "avg_rho_visit": 1.5598376806090912,
    "avg_mu_capacity": 255.6,
    "avg_sigma_capacity": 1.1
  },
  {
    "iteration": 11,
    "subproblem_original_cost": 470.0,
    "num_routes_generated": 5,
    "max_abs_g_i": 1.0,
    "avg_abs_g_i": 0.816496580927726,
    "max_cap_violation": 0.0,
    "avg_cap_violation": 0.0,
    "is_feasible_overall": false,
    "best_feasible_cost": Infinity,
    "avg_lambda_visit": -6.70672539579091,
    "avg_rho_visit": 1.6706725395790911,
    "avg_mu_capacity": 255.6,
    "avg_sigma_capacity": 1.1
  },
  {
    "iteration": 12,
    "subproblem_original_cost": 470.0,
    "num_routes_generated": 5,
    "max_abs_g_i": 1.0,
    "avg_abs_g_i": 0.816496580927726,
    "max_cap_violation": 0.0,
    "avg_cap_violation": 0.0,
    "is_feasible_overall": false,
    "best_feasible_cost": Infinity,
    "avg_lambda_visit": -7.925908844460907,
    "avg_rho_visit": 1.7925908844460923,
    "avg_mu_capacity": 255.6,
    "avg_sigma_capacity": 1.1
  },
  {
    "iteration": 13,
    "subproblem_original_cost": 595.0,
    "num_routes_generated": 5,
    "max_abs_g_i": 1.0,
    "avg_abs_g_i": 0.5222329678670935,
    "max_cap_violation": 0.0,
    "avg_cap_violation": 0.0,
    "is_feasible_overall": false,
    "best_feasible_cost": Infinity,
    "avg_lambda_visit": -8.435930995270638,
    "avg_rho_visit": 1.8435930995270655,
    "avg_mu_capacity": 255.6,
    "avg_sigma_capacity": 1.1
  },
  {
    "iteration": 14,
    "subproblem_original_cost": 506.0,
    "num_routes_generated": 5,
    "max_abs_g_i": 1.0,
    "avg_abs_g_i": 0.778498944161523,
    "max_cap_violation": 0.0,
    "avg_cap_violation": 0.0,
    "is_feasible_overall": false,
    "best_feasible_cost": Infinity,
    "avg_lambda_visit": -9.65830808527064,
    "avg_rho_visit": 1.9658308085270655,
    "avg_mu_capacity": 255.6,
    "avg_sigma_capacity": 1.1
  },
  {
    "iteration": 15,
    "subproblem_original_cost": 506.0,
    "num_routes_generated": 5,
    "max_abs_g_i": 1.0,
    "avg_abs_g_i": 0.778498944161523,
    "max_cap_violation": 0.0,
    "avg_cap_violation": 0.0,
    "is_feasible_overall": false,
    "best_feasible_cost": Infinity,
    "avg_lambda_visit": -11.002922884270644,
    "avg_rho_visit": 2.100292288427065,
    "avg_mu_capacity": 255.6,
    "avg_sigma_capacity": 1.1
  },
  {
    "iteration": 16,
    "subproblem_original_cost": 506.0,
    "num_routes_generated": 5,
    "max_abs_g_i": 1.0,
    "avg_abs_g_i": 0.778498944161523,
    "max_cap_violation": 0.0,
    "avg_cap_violation": 0.0,
    "is_feasible_overall": false,
    "best_feasible_cost": Infinity,
    "avg_lambda_visit": -12.481999163170643,
    "avg_rho_visit": 2.248199916317066,
    "avg_mu_capacity": 255.6,
    "avg_sigma_capacity": 1.1
  },
  {
    "iteration": 17,
    "subproblem_original_cost": 506.0,
    "num_routes_generated": 5,
    "max_abs_g_i": 1.0,
    "avg_abs_g_i": 0.778498944161523,
    "max_cap_violation": 0.0,
    "avg_cap_violation": 0.0,
    "is_feasible_overall": false,
    "best_feasible_cost": Infinity,
    "avg_lambda_visit": -14.108983069960646,
    "avg_rho_visit": 2.4108983069960663,
    "avg_mu_capacity": 255.6,
    "avg_sigma_capacity": 1.1
  },
  {
    "iteration": 18,
    "subproblem_original_cost": 673.0,
    "num_routes_generated": 5,
    "max_abs_g_i": 1.0,
    "avg_abs_g_i": 0.3892494720807615,
    "max_cap_violation": 0.0,
    "avg_cap_violation": 0.0,
    "is_feasible_overall": false,
    "best_feasible_cost": Infinity,
    "avg_lambda_visit": -14.523596544928676,
    "avg_rho_visit": 2.4523596544928696,
    "avg_mu_capacity": 255.6,
    "avg_sigma_capacity": 1.1
  },
  {
    "iteration": 19,
    "subproblem_original_cost": 683.0,
    "num_routes_generated": 5,
    "max_abs_g_i": 1.0,
    "avg_abs_g_i": 0.3481553119113957,
    "max_cap_violation": 0.0,
    "avg_cap_violation": 0.0,
    "is_feasible_overall": false,
    "best_feasible_cost": Infinity,
    "avg_lambda_visit": -14.859183062785478,
    "avg_rho_visit": 2.48591830627855,
    "avg_mu_capacity": 255.6,
    "avg_sigma_capacity": 1.1
  },
  {
    "iteration": 20,
    "subproblem_original_cost": 711.0,
    "num_routes_generated": 5,
    "max_abs_g_i": 1.0,
    "avg_abs_g_i": 0.3481553119113957,
    "max_cap_violation": 0.0,
    "avg_cap_violation": 0.0,
    "is_feasible_overall": false,
    "best_feasible_cost": Infinity,
    "avg_lambda_visit": -15.138411621233542,
    "avg_rho_visit": 2.5138411621233563,
    "avg_mu_capacity": 255.6,
    "avg_sigma_capacity": 1.1
  },
  {
    "iteration": 21,
    "subproblem_original_cost": 538.0,
    "num_routes_generated": 5,
    "max_abs_g_i": 1.0,
    "avg_abs_g_i": 0.7385489458759964,
    "max_cap_violation": 0.0,
    "avg_cap_violation": 0.0,
    "is_feasible_overall": false,
    "best_feasible_cost": Infinity,
    "avg_lambda_visit": -16.684624615191122,
    "avg_rho_visit": 2.6684624615191144,
    "avg_mu_capacity": 255.6,
    "avg_sigma_capacity": 1.1
  },
  {
    "iteration": 22,
    "subproblem_original_cost": 738.0,
    "num_routes_generated": 5,
    "max_abs_g_i": 1.0,
    "avg_abs_g_i": 0.3481553119113957,
    "max_cap_violation": 0.0,
    "avg_cap_violation": 0.0,
    "is_feasible_overall": false,
    "best_feasible_cost": Infinity,
    "avg_lambda_visit": -16.99995026686531,
    "avg_rho_visit": 2.6999950266865325,
    "avg_mu_capacity": 255.6,
    "avg_sigma_capacity": 1.1
  },
  {
    "iteration": 23,
    "subproblem_original_cost": 739.0,
    "num_routes_generated": 5,
    "max_abs_g_i": 1.0,
    "avg_abs_g_i": 0.5222329678670935,
    "max_cap_violation": 0.0,
    "avg_cap_violation": 0.0,
    "is_feasible_overall": false,
    "best_feasible_cost": Infinity,
    "avg_lambda_visit": -17.43136082373564,
    "avg_rho_visit": 2.7431360823735664,
    "avg_mu_capacity": 255.6,
    "avg_sigma_capacity": 1.1
  },
  {
    "iteration": 24,
    "subproblem_original_cost": 704.0,
    "num_routes_generated": 5,
    "max_abs_g_i": 1.0,
    "avg_abs_g_i": 0.4264014327112209,
    "max_cap_violation": 0.0,
    "avg_cap_violation": 0.0,
    "is_feasible_overall": false,
    "best_feasible_cost": Infinity,
    "avg_lambda_visit": -17.889861645166675,
    "avg_rho_visit": 2.78898616451667,
    "avg_mu_capacity": 255.6,
    "avg_sigma_capacity": 1.1
  },
  {
    "iteration": 25,
    "subproblem_original_cost": 728.0,
    "num_routes_generated": 5,
    "max_abs_g_i": 1.0,
    "avg_abs_g_i": 0.3481553119113957,
    "max_cap_violation": 0.0,
    "avg_cap_violation": 0.0,
    "is_feasible_overall": false,
    "best_feasible_cost": Infinity,
    "avg_lambda_visit": -18.235089929931043,
    "avg_rho_visit": 2.8235089929931068,
    "avg_mu_capacity": 255.6,
    "avg_sigma_capacity": 1.1
  },
  {
    "iteration": 26,
    "subproblem_original_cost": 747.0,
    "num_routes_generated": 5,
    "max_abs_g_i": 1.0,
    "avg_abs_g_i": 0.5504818825631803,
    "max_cap_violation": 0.0,
    "avg_cap_violation": 0.0,
    "is_feasible_overall": false,
    "best_feasible_cost": Infinity,
    "avg_lambda_visit": -18.741437460264375,
    "avg_rho_visit": 2.87414374602644,
    "avg_mu_capacity": 255.6,
    "avg_sigma_capacity": 1.1
  },
  {
    "iteration": 27,
    "subproblem_original_cost": 720.0,
    "num_routes_generated": 5,
    "max_abs_g_i": 1.0,
    "avg_abs_g_i": 0.3892494720807615,
    "max_cap_violation": 0.0,
    "avg_cap_violation": 0.0,
    "is_feasible_overall": false,
    "best_feasible_cost": Infinity,
    "avg_lambda_visit": -19.190415443432745,
    "avg_rho_visit": 2.9190415443432767,
    "avg_mu_capacity": 255.6,
    "avg_sigma_capacity": 1.1
  },
  {
    "iteration": 28,
    "subproblem_original_cost": 709.0,
    "num_routes_generated": 5,
    "max_abs_g_i": 1.0,
    "avg_abs_g_i": 0.3892494720807615,
    "max_cap_violation": 0.0,
    "avg_cap_violation": 0.0,
    "is_feasible_overall": false,
    "best_feasible_cost": Infinity,
    "avg_lambda_visit": -19.716435060149223,
    "avg_rho_visit": 2.9716435060149244,
    "avg_mu_capacity": 255.6,
    "avg_sigma_capacity": 1.1
  },
  {
    "iteration": 29,
    "subproblem_original_cost": 720.0,
    "num_routes_generated": 5,
    "max_abs_g_i": 1.0,
    "avg_abs_g_i": 0.3892494720807615,
    "max_cap_violation": 0.0,
    "avg_cap_violation": 0.0,
    "is_feasible_overall": false,
    "best_feasible_cost": Infinity,
    "avg_lambda_visit": -20.2708907400366,
    "avg_rho_visit": 3.027089074003662,
    "avg_mu_capacity": 255.6,
    "avg_sigma_capacity": 1.1
  },
  {
    "iteration": 30,
    "subproblem_original_cost": 758.0,
    "num_routes_generated": 5,
    "max_abs_g_i": 1.0,
    "avg_abs_g_i": 0.5504818825631803,
    "max_cap_violation": 0.0,
    "avg_cap_violation": 0.0,
    "is_feasible_overall": false,
    "best_feasible_cost": Infinity,
    "avg_lambda_visit": -20.851523953273603,
    "avg_rho_visit": 3.0851523953273627,
    "avg_mu_capacity": 255.6,
    "avg_sigma_capacity": 1.1
  },
  {
    "iteration": 31,
    "subproblem_original_cost": 720.0,
    "num_routes_generated": 5,
    "max_abs_g_i": 1.0,
    "avg_abs_g_i": 0.4264014327112209,
    "max_cap_violation": 0.0,
    "avg_cap_violation": 0.0,
    "is_feasible_overall": false,
    "best_feasible_cost": Infinity,
    "avg_lambda_visit": -21.411155107488124,
    "avg_rho_visit": 3.1411155107488145,
    "avg_mu_capacity": 255.6,
    "avg_sigma_capacity": 1.1
  },
  {
    "iteration": 32,
    "subproblem_original_cost": 748.0,
    "num_routes_generated": 5,
    "max_abs_g_i": 1.0,
    "avg_abs_g_i": 0.24618298195866548,
    "max_cap_violation": 0.0,
    "avg_cap_violation": 0.0,
    "is_feasible_overall": false,
    "best_feasible_cost": Infinity,
    "avg_lambda_visit": -21.67697999099639,
    "avg_rho_visit": 3.1676979990996412,
    "avg_mu_capacity": 255.6,
    "avg_sigma_capacity": 1.1
  },
  {
    "iteration": 33,
    "subproblem_original_cost": 787.0,
    "num_routes_generated": 5,
    "max_abs_g_i": 1.0,
    "avg_abs_g_i": 0.24618298195866548,
    "max_cap_violation": 0.0,
    "avg_cap_violation": 0.0,
    "is_feasible_overall": false,
    "best_feasible_cost": Infinity,
    "avg_lambda_visit": -21.86058826331025,
    "avg_rho_visit": 3.186058826331027,
    "avg_mu_capacity": 255.6,
    "avg_sigma_capacity": 1.1
  },
  {
    "iteration": 34,
    "subproblem_original_cost": 794.0,
    "num_routes_generated": 5,
    "max_abs_g_i": 1.0,
    "avg_abs_g_i": 0.49236596391733095,
    "max_cap_violation": 0.0,
    "avg_cap_violation": 0.0,
    "is_feasible_overall": false,
    "best_feasible_cost": Infinity,
    "avg_lambda_visit": -22.30821243664358,
    "avg_rho_visit": 3.2308212436643604,
    "avg_mu_capacity": 255.6,
    "avg_sigma_capacity": 1.1
  },
  {
    "iteration": 35,
    "subproblem_original_cost": 742.0,
    "num_routes_generated": 5,
    "max_abs_g_i": 1.0,
    "avg_abs_g_i": 0.3892494720807615,
    "max_cap_violation": 0.0,
    "avg_cap_violation": 0.0,
    "is_feasible_overall": false,
    "best_feasible_cost": Infinity,
    "avg_lambda_visit": -22.906606113805047,
    "avg_rho_visit": 3.2906606113805075,
    "avg_mu_capacity": 255.6,
    "avg_sigma_capacity": 1.1
  },
  {
    "iteration": 36,
    "subproblem_original_cost": 806.0,
    "num_routes_generated": 5,
    "max_abs_g_i": 1.0,
    "avg_abs_g_i": 0.3481553119113957,
    "max_cap_violation": 0.0,
    "avg_cap_violation": 0.0,
    "is_feasible_overall": false,
    "best_feasible_cost": Infinity,
    "avg_lambda_visit": -23.17349773734205,
    "avg_rho_visit": 3.3173497737342075,
    "avg_mu_capacity": 255.6,
    "avg_sigma_capacity": 1.1
  },
  {
    "iteration": 37,
    "subproblem_original_cost": 808.0,
    "num_routes_generated": 5,
    "max_abs_g_i": 1.0,
    "avg_abs_g_i": 0.3481553119113957,
    "max_cap_violation": 0.0,
    "avg_cap_violation": 0.0,
    "is_feasible_overall": false,
    "best_feasible_cost": Infinity,
    "avg_lambda_visit": -23.502688541569796,
    "avg_rho_visit": 3.350268854156982,
    "avg_mu_capacity": 255.6,
    "avg_sigma_capacity": 1.1
  },
  {
    "iteration": 38,
    "subproblem_original_cost": 812.0,
    "num_routes_generated": 5,
    "max_abs_g_i": 1.0,
    "avg_abs_g_i": 0.3481553119113957,
    "max_cap_violation": 0.0,
    "avg_cap_violation": 0.0,
    "is_feasible_overall": false,
    "best_feasible_cost": Infinity,
    "avg_lambda_visit": -23.837392377550316,
    "avg_rho_visit": 3.383739237755034,
    "avg_mu_capacity": 255.6,
    "avg_sigma_capacity": 1.1
  },
  {
    "iteration": 39,
    "subproblem_original_cost": 752.0,
    "num_routes_generated": 5,
    "max_abs_g_i": 1.0,
    "avg_abs_g_i": 0.24618298195866548,
    "max_cap_violation": 0.0,
    "avg_cap_violation": 0.0,
    "is_feasible_overall": false,
    "best_feasible_cost": Infinity,
    "avg_lambda_visit": -24.129799749409415,
    "avg_rho_visit": 3.412979974940944,
    "avg_mu_capacity": 255.6,
    "avg_sigma_capacity": 1.1
  },
  {
    "iteration": 40,
    "subproblem_original_cost": 865.0,
    "num_routes_generated": 5,
    "max_abs_g_i": 1.0,
    "avg_abs_g_i": 0.3481553119113957,
    "max_cap_violation": 0.0,
    "avg_cap_violation": 0.0,
    "is_feasible_overall": false,
    "best_feasible_cost": Infinity,
    "avg_lambda_visit": -24.468179045954656,
    "avg_rho_visit": 3.446817904595468,
    "avg_mu_capacity": 255.6,
    "avg_sigma_capacity": 1.1
  },
  {
    "iteration": 41,
    "subproblem_original_cost": 743.0,
    "num_routes_generated": 5,
    "max_abs_g_i": 1.0,
    "avg_abs_g_i": 0.3892494720807615,
    "max_cap_violation": 0.0,
    "avg_cap_violation": 0.0,
    "is_feasible_overall": false,
    "best_feasible_cost": Infinity,
    "avg_lambda_visit": -25.126412090832275,
    "avg_rho_visit": 3.5126412090832297,
    "avg_mu_capacity": 255.6,
    "avg_sigma_capacity": 1.1
  },
  {
    "iteration": 42,
    "subproblem_original_cost": 808.0,
    "num_routes_generated": 5,
    "max_abs_g_i": 1.0,
    "avg_abs_g_i": 0.3892494720807615,
    "max_cap_violation": 0.0,
    "avg_cap_violation": 0.0,
    "is_feasible_overall": false,
    "best_feasible_cost": Infinity,
    "avg_lambda_visit": -25.507578315726306,
    "avg_rho_visit": 3.5507578315726325,
    "avg_mu_capacity": 255.6,
    "avg_sigma_capacity": 1.1
  },
  {
    "iteration": 43,
    "subproblem_original_cost": 817.0,
    "num_routes_generated": 5,
    "max_abs_g_i": 1.0,
    "avg_abs_g_i": 0.3481553119113957,
    "max_cap_violation": 0.0,
    "avg_cap_violation": 0.0,
    "is_feasible_overall": false,
    "best_feasible_cost": Infinity,
    "avg_lambda_visit": -25.875469394440163,
    "avg_rho_visit": 3.5875469394440183,
    "avg_mu_capacity": 255.6,
    "avg_sigma_capacity": 1.1
  },
  {
    "iteration": 44,
    "subproblem_original_cost": 807.0,
    "num_routes_generated": 5,
    "max_abs_g_i": 1.0,
    "avg_abs_g_i": 0.3892494720807615,
    "max_cap_violation": 0.0,
    "avg_cap_violation": 0.0,
    "is_feasible_overall": false,
    "best_feasible_cost": Infinity,
    "avg_lambda_visit": -26.332842300889073,
    "avg_rho_visit": 3.633284230088909,
    "avg_mu_capacity": 255.6,
    "avg_sigma_capacity": 1.1
  },
  {
    "iteration": 45,
    "subproblem_original_cost": 814.0,
    "num_routes_generated": 5,
    "max_abs_g_i": 1.0,
    "avg_abs_g_i": 0.24618298195866548,
    "max_cap_violation": 0.0,
    "avg_cap_violation": 0.0,
    "is_feasible_overall": false,
    "best_feasible_cost": Infinity,
    "avg_lambda_visit": -26.555008310388835,
    "avg_rho_visit": 3.6555008310388857,
    "avg_mu_capacity": 255.6,
    "avg_sigma_capacity": 1.1
  },
  {
    "iteration": 46,
    "subproblem_original_cost": 748.0,
    "num_routes_generated": 5,
    "max_abs_g_i": 1.0,
    "avg_abs_g_i": 0.4264014327112209,
    "max_cap_violation": 0.0,
    "avg_cap_violation": 0.0,
    "is_feasible_overall": false,
    "best_feasible_cost": Infinity,
    "avg_lambda_visit": -27.300500125567225,
    "avg_rho_visit": 3.730050012556724,
    "avg_mu_capacity": 255.6,
    "avg_sigma_capacity": 1.1
  },
  {
    "iteration": 47,
    "subproblem_original_cost": 675.0,
    "num_routes_generated": 5,
    "max_abs_g_i": 1.0,
    "avg_abs_g_i": 0.6963106238227914,
    "max_cap_violation": 0.0,
    "avg_cap_violation": 0.0,
    "is_feasible_overall": false,
    "best_feasible_cost": Infinity,
    "avg_lambda_visit": -29.057264537950612,
    "avg_rho_visit": 3.9057264537950633,
    "avg_mu_capacity": 255.6,
    "avg_sigma_capacity": 1.1
  },
  {
    "iteration": 48,
    "subproblem_original_cost": 804.0,
    "num_routes_generated": 5,
    "max_abs_g_i": 1.0,
    "avg_abs_g_i": 0.30151134457776363,
    "max_cap_violation": 0.0,
    "avg_cap_violation": 0.0,
    "is_feasible_overall": false,
    "best_feasible_cost": Infinity,
    "avg_lambda_visit": -29.436129991813043,
    "avg_rho_visit": 3.9436129991813065,
    "avg_mu_capacity": 255.6,
    "avg_sigma_capacity": 1.1
  },
  {
    "iteration": 49,
    "subproblem_original_cost": 819.0,
    "num_routes_generated": 5,
    "max_abs_g_i": 1.0,
    "avg_abs_g_i": 0.24618298195866548,
    "max_cap_violation": 0.0,
    "avg_cap_violation": 0.0,
    "is_feasible_overall": false,
    "best_feasible_cost": Infinity,
    "avg_lambda_visit": -29.68051260226278,
    "avg_rho_visit": 3.9680512602262814,
    "avg_mu_capacity": 255.6,
    "avg_sigma_capacity": 1.1
  },
  {
    "iteration": 50,
    "subproblem_original_cost": 833.0,
    "num_routes_generated": 5,
    "max_abs_g_i": 1.0,
    "avg_abs_g_i": 0.30151134457776363,
    "max_cap_violation": 0.0,
    "avg_cap_violation": 0.0,
    "is_feasible_overall": false,
    "best_feasible_cost": Infinity,
    "avg_lambda_visit": -29.940672830836448,
    "avg_rho_visit": 3.994067283083648,
    "avg_mu_capacity": 255.6,
    "avg_sigma_capacity": 1.1
  },
  {
    "iteration": 51,
    "subproblem_original_cost": 833.0,
    "num_routes_generated": 5,
    "max_abs_g_i": 1.0,
    "avg_abs_g_i": 0.30151134457776363,
    "max_cap_violation": 0.0,
    "avg_cap_violation": 0.0,
    "is_feasible_overall": false,
    "best_feasible_cost": Infinity,
    "avg_lambda_visit": -30.226849082267485,
    "avg_rho_visit": 4.022684908226751,
    "avg_mu_capacity": 255.6,
    "avg_sigma_capacity": 1.1
  },
  {
    "iteration": 52,
    "subproblem_original_cost": 750.0,
    "num_routes_generated": 5,
    "max_abs_g_i": 1.0,
    "avg_abs_g_i": 0.3892494720807615,
    "max_cap_violation": 0.0,
    "avg_cap_violation": 0.0,
    "is_feasible_overall": false,
    "best_feasible_cost": Infinity,
    "avg_lambda_visit": -30.87280525241679,
    "avg_rho_visit": 4.087280525241681,
    "avg_mu_capacity": 255.6,
    "avg_sigma_capacity": 1.1
  },
  {
    "iteration": 53,
    "subproblem_original_cost": 748.0,
    "num_routes_generated": 5,
    "max_abs_g_i": 1.0,
    "avg_abs_g_i": 0.30151134457776363,
    "max_cap_violation": 0.0,
    "avg_cap_violation": 0.0,
    "is_feasible_overall": false,
    "best_feasible_cost": Infinity,
    "avg_lambda_visit": -31.333694967108986,
    "avg_rho_visit": 4.1333694967109,
    "avg_mu_capacity": 255.6,
    "avg_sigma_capacity": 1.1
  },
  {
    "iteration": 54,
    "subproblem_original_cost": 784.0,
    "num_routes_generated": 5,
    "max_abs_g_i": 1.0,
    "avg_abs_g_i": 0.17407765595569785,
    "max_cap_violation": 0.0,
    "avg_cap_violation": 0.0,
    "is_feasible_overall": false,
    "best_feasible_cost": Infinity,
    "avg_lambda_visit": -31.50217730994208,
    "avg_rho_visit": 4.150217730994211,
    "avg_mu_capacity": 255.6,
    "avg_sigma_capacity": 1.1
  },
  {
    "iteration": 55,
    "subproblem_original_cost": 748.0,
    "num_routes_generated": 5,
    "max_abs_g_i": 1.0,
    "avg_abs_g_i": 0.4264014327112209,
    "max_cap_violation": 0.0,
    "avg_cap_violation": 0.0,
    "is_feasible_overall": false,
    "best_feasible_cost": Infinity,
    "avg_lambda_visit": -32.333725877352954,
    "avg_rho_visit": 4.233372587735297,
    "avg_mu_capacity": 255.6,
    "avg_sigma_capacity": 1.1
  },
  {
    "iteration": 56,
    "subproblem_original_cost": 926.0,
    "num_routes_generated": 5,
    "max_abs_g_i": 1.0,
    "avg_abs_g_i": 0.17407765595569785,
    "max_cap_violation": 0.0,
    "avg_cap_violation": 0.0,
    "is_feasible_overall": false,
    "best_feasible_cost": Infinity,
    "avg_lambda_visit": -32.42018395935628,
    "avg_rho_visit": 4.242018395935631,
    "avg_mu_capacity": 255.6,
    "avg_sigma_capacity": 1.1
  },
  {
    "iteration": 57,
    "subproblem_original_cost": 929.0,
    "num_routes_generated": 5,
    "max_abs_g_i": 1.0,
    "avg_abs_g_i": 0.24618298195866548,
    "max_cap_violation": 0.0,
    "avg_cap_violation": 0.0,
    "is_feasible_overall": false,
    "best_feasible_cost": Infinity,
    "avg_lambda_visit": -32.56308988002295,
    "avg_rho_visit": 4.2563089880022975,
    "avg_mu_capacity": 255.6,
    "avg_sigma_capacity": 1.1
  },
  {
    "iteration": 58,
    "subproblem_original_cost": 926.0,
    "num_routes_generated": 5,
    "max_abs_g_i": 1.0,
    "avg_abs_g_i": 0.17407765595569785,
    "max_cap_violation": 0.0,
    "avg_cap_violation": 0.0,
    "is_feasible_overall": false,
    "best_feasible_cost": Infinity,
    "avg_lambda_visit": -32.65819377022662,
    "avg_rho_visit": 4.265819377022664,
    "avg_mu_capacity": 255.6,
    "avg_sigma_capacity": 1.1
  },
  {
    "iteration": 59,
    "subproblem_original_cost": 921.0,
    "num_routes_generated": 5,
    "max_abs_g_i": 1.0,
    "avg_abs_g_i": 0.17407765595569785,
    "max_cap_violation": 0.0,
    "avg_cap_violation": 0.0,
    "is_feasible_overall": false,
    "best_feasible_cost": Infinity,
    "avg_lambda_visit": -32.75329766043029,
    "avg_rho_visit": 4.275329766043031,
    "avg_mu_capacity": 255.6,
    "avg_sigma_capacity": 1.1
  },
  {
    "iteration": 60,
    "subproblem_original_cost": 848.0,
    "num_routes_generated": 5,
    "max_abs_g_i": 0.0,
    "avg_abs_g_i": 0.0,
    "max_cap_violation": 0.0,
    "avg_cap_violation": 0.0,
    "is_feasible_overall": true,
    "best_feasible_cost": 848.0,
    "avg_lambda_visit": -32.75329766043029,
    "avg_rho_visit": 4.275329766043031,
    "avg_mu_capacity": 255.6,
    "avg_sigma_capacity": 1.1
  }
]