[
  {
    "iteration": 1,
    "subproblem_original_cost": 258.0,
    "num_routes_generated": 10,
    "max_abs_g_i": 1.0,
    "avg_abs_g_i": 0.9486832980505138,
    "is_feasible_overall": false,
    "best_feasible_cost": Infinity,
    "avg_lambda": -0.9,
    "avg_rho": 1.0899999999999983
  },
  {
    "iteration": 2,
    "subproblem_original_cost": 258.0,
    "num_routes_generated": 10,
    "max_abs_g_i": 1.0,
    "avg_abs_g_i": 0.9486832980505138,
    "is_feasible_overall": false,
    "best_feasible_cost": Infinity,
    "avg_lambda": -1.8899999999999968,
    "avg_rho": 1.1889999999999976
  },
  {
    "iteration": 3,
    "subproblem_original_cost": 266.0,
    "num_routes_generated": 10,
    "max_abs_g_i": 1.0,
    "avg_abs_g_i": 0.9433981132056604,
    "is_feasible_overall": false,
    "best_feasible_cost": Infinity,
    "avg_lambda": -2.9606000000000017,
    "avg_rho": 1.296060000000002
  },
  {
    "iteration": 4,
    "subproblem_original_cost": 323.0,
    "num_routes_generated": 10,
    "max_abs_g_i": 1.0,
    "avg_abs_g_i": 0.812403840463596,
    "is_feasible_overall": false,
    "best_feasible_cost": Infinity,
    "avg_lambda": -3.8355400000000044,
    "avg_rho": 1.3835540000000017
  },
  {
    "iteration": 5,
    "subproblem_original_cost": 341.0,
    "num_routes_generated": 10,
    "max_abs_g_i": 1.0,
    "avg_abs_g_i": 0.7937253933193772,
    "is_feasible_overall": false,
    "best_feasible_cost": Infinity,
    "avg_lambda": -4.745085999999999,
    "avg_rho": 1.4745086000000023
  },
  {
    "iteration": 6,
    "subproblem_original_cost": 408.0,
    "num_routes_generated": 10,
    "max_abs_g_i": 1.0,
    "avg_abs_g_i": 0.6928203230275509,
    "is_feasible_overall": false,
    "best_feasible_cost": Infinity,
    "avg_lambda": -5.507766500000005,
    "avg_rho": 1.5507766500000013
  },
  {
    "iteration": 7,
    "subproblem_original_cost": 448.0,
    "num_routes_generated": 10,
    "max_abs_g_i": 1.0,
    "avg_abs_g_i": 0.7,
    "is_feasible_overall": false,
    "best_feasible_cost": Infinity,
    "avg_lambda": -6.310874849999999,
    "avg_rho": 1.6310874850000017
  },
  {
    "iteration": 8,
    "subproblem_original_cost": 598.0,
    "num_routes_generated": 10,
    "max_abs_g_i": 1.0,
    "avg_abs_g_i": 0.5385164807134504,
    "is_feasible_overall": false,
    "best_feasible_cost": Infinity,
    "avg_lambda": -6.812622809000001,
    "avg_rho": 1.6812622809000017
  },
  {
    "iteration": 9,
    "subproblem_original_cost": 669.0,
    "num_routes_generated": 10,
    "max_abs_g_i": 1.0,
    "avg_abs_g_i": 0.5,
    "is_feasible_overall": false,
    "best_feasible_cost": Infinity,
    "avg_lambda": -7.228359549200004,
    "avg_rho": 1.722835954920002
  },
  {
    "iteration": 10,
    "subproblem_original_cost": 763.0,
    "num_routes_generated": 10,
    "max_abs_g_i": 1.0,
    "avg_abs_g_i": 0.4,
    "is_feasible_overall": false,
    "best_feasible_cost": Infinity,
    "avg_lambda": -7.467725489300006,
    "avg_rho": 1.7467725489300023
  },
  {
    "iteration": 11,
    "subproblem_original_cost": 769.0,
    "num_routes_generated": 10,
    "max_abs_g_i": 1.0,
    "avg_abs_g_i": 0.33166247903553997,
    "is_feasible_overall": false,
    "best_feasible_cost": Infinity,
    "avg_lambda": -7.649061678400006,
    "avg_rho": 1.7649061678400022
  },
  {
    "iteration": 12,
    "subproblem_original_cost": 752.0,
    "num_routes_generated": 10,
    "max_abs_g_i": 1.0,
    "avg_abs_g_i": 0.31622776601683794,
    "is_feasible_overall": false,
    "best_feasible_cost": Infinity,
    "avg_lambda": -7.848948754910006,
    "avg_rho": 1.7848948754910028
  },
  {
    "iteration": 13,
    "subproblem_original_cost": 802.0,
    "num_routes_generated": 10,
    "max_abs_g_i": 1.0,
    "avg_abs_g_i": 0.2449489742783178,
    "is_feasible_overall": false,
    "best_feasible_cost": Infinity,
    "avg_lambda": -7.946717702110005,
    "avg_rho": 1.7946717702110033
  },
  {
    "iteration": 14,
    "subproblem_original_cost": 803.0,
    "num_routes_generated": 10,
    "max_abs_g_i": 1.0,
    "avg_abs_g_i": 0.2449489742783178,
    "is_feasible_overall": false,
    "best_feasible_cost": Infinity,
    "avg_lambda": -8.045789167120006,
    "avg_rho": 1.8045789167120032
  },
  {
    "iteration": 15,
    "subproblem_original_cost": 793.0,
    "num_routes_generated": 10,
    "max_abs_g_i": 1.0,
    "avg_abs_g_i": 0.2645751311064591,
    "is_feasible_overall": false,
    "best_feasible_cost": Infinity,
    "avg_lambda": -8.176511127731008,
    "avg_rho": 1.8176511127731032
  },
  {
    "iteration": 16,
    "subproblem_original_cost": 803.0,
    "num_routes_generated": 10,
    "max_abs_g_i": 1.0,
    "avg_abs_g_i": 0.2645751311064591,
    "is_feasible_overall": false,
    "best_feasible_cost": Infinity,
    "avg_lambda": -8.302246934741007,
    "avg_rho": 1.8302246934741035
  },
  {
    "iteration": 17,
    "subproblem_original_cost": 794.0,
    "num_routes_generated": 10,
    "max_abs_g_i": 1.0,
    "avg_abs_g_i": 0.2449489742783178,
    "is_feasible_overall": false,
    "best_feasible_cost": Infinity,
    "avg_lambda": -8.429935991413105,
    "avg_rho": 1.8429935991413133
  },
  {
    "iteration": 18,
    "subproblem_original_cost": 834.0,
    "num_routes_generated": 10,
    "max_abs_g_i": 1.0,
    "avg_abs_g_i": 0.1414213562373095,
    "is_feasible_overall": false,
    "best_feasible_cost": Infinity,
    "avg_lambda": -8.470514416014105,
    "avg_rho": 1.8470514416014134
  },
  {
    "iteration": 19,
    "subproblem_original_cost": 829.0,
    "num_routes_generated": 10,
    "max_abs_g_i": 1.0,
    "avg_abs_g_i": 0.1414213562373095,
    "is_feasible_overall": false,
    "best_feasible_cost": Infinity,
    "avg_lambda": -8.517673369834105,
    "avg_rho": 1.8517673369834131
  },
  {
    "iteration": 20,
    "subproblem_original_cost": 830.0,
    "num_routes_generated": 10,
    "max_abs_g_i": 1.0,
    "avg_abs_g_i": 0.17320508075688773,
    "is_feasible_overall": false,
    "best_feasible_cost": Infinity,
    "avg_lambda": -8.575486536895204,
    "avg_rho": 1.8575486536895232
  },
  {
    "iteration": 21,
    "subproblem_original_cost": 831.0,
    "num_routes_generated": 10,
    "max_abs_g_i": 1.0,
    "avg_abs_g_i": 0.1414213562373095,
    "is_feasible_overall": false,
    "best_feasible_cost": Infinity,
    "avg_lambda": -8.622645490715204,
    "avg_rho": 1.862264549071523
  },
  {
    "iteration": 22,
    "subproblem_original_cost": 835.0,
    "num_routes_generated": 10,
    "max_abs_g_i": 1.0,
    "avg_abs_g_i": 0.1,
    "is_feasible_overall": false,
    "best_feasible_cost": Infinity,
    "avg_lambda": -8.651176657776304,
    "avg_rho": 1.8651176657776332
  },
  {
    "iteration": 23,
    "subproblem_original_cost": 835.0,
    "num_routes_generated": 10,
    "max_abs_g_i": 1.0,
    "avg_abs_g_i": 0.1414213562373095,
    "is_feasible_overall": false,
    "best_feasible_cost": Infinity,
    "avg_lambda": -8.678281757776304,
    "avg_rho": 1.8678281757776332
  },
  {
    "iteration": 24,
    "subproblem_original_cost": 839.0,
    "num_routes_generated": 10,
    "max_abs_g_i": 1.0,
    "avg_abs_g_i": 0.1,
    "is_feasible_overall": false,
    "best_feasible_cost": Infinity,
    "avg_lambda": -8.697768928776304,
    "avg_rho": 1.8697768928776333
  },
  {
    "iteration": 25,
    "subproblem_original_cost": 835.0,
    "num_routes_generated": 10,
    "max_abs_g_i": 1.0,
    "avg_abs_g_i": 0.1,
    "is_feasible_overall": false,
    "best_feasible_cost": Infinity,
    "avg_lambda": -8.721348405686305,
    "avg_rho": 1.872134840568633
  },
  {
    "iteration": 26,
    "subproblem_original_cost": 842.0,
    "num_routes_generated": 10,
    "max_abs_g_i": 0.0,
    "avg_abs_g_i": 0.0,
    "is_feasible_overall": true,
    "best_feasible_cost": 842.0,
    "avg_lambda": -8.721348405686305,
    "avg_rho": 1.872134840568633
  }
]